{"version": "1", "message": "ERROR: Hidden Testcases server unreachable.", "problem_id": "ads2_m10_a1_1", "user_id": "pranay0124@msitprogram.net", "score": {"sample": {"0": {"execution_time": 0.4490344524383545, "passed": true}, "1": {"execution_time": 0.4104127883911133, "passed": true}, "2": {"execution_time": 0.12666010856628418, "passed": false}, "3": {"execution_time": 0.1226205825805664, "passed": false}, "4": {"execution_time": 0.13812041282653809, "passed": false}, "5": {"execution_time": 0.14564228057861328, "passed": false}, "6": {"execution_time": 0.1391744613647461, "passed": false}, "7": {"execution_time": 0.13464069366455078, "passed": false}, "8": {"execution_time": 0.12161898612976074, "passed": false}}}, "check_style_score": "0/1"}